README.rst
setup.py
unirep_analysis.py
src/custom_models.py
src/data_utils.py
src/unirep.py
unirep_analysis.egg-info/PKG-INFO
unirep_analysis.egg-info/SOURCES.txt
unirep_analysis.egg-info/dependency_links.txt
unirep_analysis.egg-info/entry_points.txt
unirep_analysis.egg-info/not-zip-safe
unirep_analysis.egg-info/top_level.txt