Metadata-Version: 2.1
Name: unirep-analysis
Version: 0.2.8
Summary: An app to run UniRep analysis
Home-page: http://wiki
Author: Sandip Samal
Author-email: dev@babyMRI.org
License: MIT
Platform: UNKNOWN
Requires-Python: >=3.5
